palettize/__init__.py
palettize/cli.py
palettize/core.py
palettize/exceptions.py
palettize/presets.py
palettize/py.typed
palettize/scaling.py
palettize/exporters/__init__.py
palettize/exporters/_base.py
palettize/exporters/gdal.py
palettize/exporters/gee.py
palettize/exporters/mapgl.py
palettize/exporters/observable_plot.py
palettize/exporters/plaintext.py
palettize/exporters/qgis.py
palettize/exporters/sld.py
palettize/exporters/titiler.py
palettize-0.0.1a3.dist-info/licenses/LICENSE
palettize-0.0.1a3.dist-info/METADATA
palettize-0.0.1a3.dist-info/WHEEL
palettize-0.0.1a3.dist-info/entry_points.txt
palettize-0.0.1a3.dist-info/top_level.txt
palettize-0.0.1a3.dist-info/RECORD
