Metadata-Version: 2.4
Name: palettize
Version: 0.0.1a3
Summary: A Python CLI tool for creating and exporting colormaps for data visualization and mapping applications.
Author-email: Alex Kovac <5686693+kovaca@users.noreply.github.com>
License-Expression: MIT
Classifier: Development Status :: 2 - Pre-Alpha
Classifier: Intended Audience :: Developers
Classifier: Intended Audience :: Science/Research
Classifier: Programming Language :: Python :: 3
Classifier: Programming Language :: Python :: 3.9
Classifier: Programming Language :: Python :: 3.10
Classifier: Programming Language :: Python :: 3.11
Classifier: Programming Language :: Python :: 3.12
Classifier: Programming Language :: Python :: 3.13
Classifier: Topic :: Multimedia :: Graphics
Classifier: Topic :: Scientific/Engineering :: Visualization
Requires-Python: >=3.9
License-File: LICENSE
Requires-Dist: coloraide>=0.24
Requires-Dist: typer>=0.9
Requires-Dist: rich>=13.0
Requires-Dist: webcolors>=1.13
Requires-Dist: cmap>=0.6.0
Provides-Extra: dev
Requires-Dist: pytest>=8.3.5; extra == "dev"
Requires-Dist: pytest-cov>=6.1.1; extra == "dev"
Requires-Dist: ruff; extra == "dev"
Requires-Dist: mypy; extra == "dev"
Dynamic: license-file
